pymsgboxexample1996wg.py
pymsgboxexample1996wg-0.1.0.dist-info/METADATA
pymsgboxexample1996wg-0.1.0.dist-info/WHEEL
pymsgboxexample1996wg-0.1.0.dist-info/RECORD
