Metadata-Version: 2.1
Name: pymsgboxexample1996wg
Version: 0.1.0
Summary: This is a simple example script using PyMsgBox.
Author: Your Name
Author-email: you@example.com
Requires-Python: >=3.11,<4.0
Classifier: Programming Language :: Python :: 3
Classifier: Programming Language :: Python :: 3.11
Classifier: Programming Language :: Python :: 3.12
Requires-Dist: pymsgbox (>=1.0.9,<2.0.0)
